[
  {
    "image": "/assets/images/γυναικεια/παπουτσια/loafers.jpeg",
    "name": "Γυναικείες Loafers",
    "url": "γυναικεια/παπουτσια/loafers"
  },
  {
    "image": "/assets/images/γυναικεια/παπουτσια/oxford.jpeg",
    "name": "Γυναικεία Oxford",
    "url": "γυναικεια/παπουτσια/oxford"
  },
  {
    "image": "/assets/images/γυναικεια/παπουτσια/γαλοτσες.jpeg",
    "name": "Γυναικείες Γαλότσες",
    "url": "γυναικεια/παπουτσια/γαλοτσες"
  },
  {
    "image": "/assets/images/γυναικεια/παπουτσια/γοβες.jpeg",
    "name": "Γόβες",
    "url": "γυναικεια/παπουτσια/γοβες"
  },
  {
    "image": "/assets/images/γυναικεια/παπουτσια/εσπαντριγιες.jpeg",
    "name": "Γυναικείες Εσπαντρίγιες",
    "url": "γυναικεια/παπουτσια/εσπαντριγιες"
  },
  {
    "image": "/assets/images/γυναικεια/παπουτσια/μοκασινια.jpeg",
    "name": "Γυναικεία Μοκασίνια",
    "url": "γυναικεια/παπουτσια/φουστες"
  },
  {
    "image": "/assets/images/γυναικεια/παπουτσια/μπαλαρινες.jpeg",
    "name": "Μπαλαρίνες",
    "url": "γυναικεια/παπουτσια/μπαλαρινες"
  },
  {
    "image": "/assets/images/γυναικεια/παπουτσια/μποτακια.jpeg",
    "name": "Γυναικεία Μποτάκια",
    "url": "γυναικεια/παπουτσια/μποτακια"
  },
 {
    "image": "/assets/images/γυναικεια/παπουτσια/πεδιλα.jpeg",
    "name": "Γυναικείες Πέδιλα",
    "url": "γυναικεια/παπουτσια/πεδιλα"
  },
  {
    "image": "/assets/images/γυναικεια/παπουτσια/πλατφορμες.jpeg",
    "name": "Γυναικείες Πλατφόρμες",
    "url": "γυναικεια/παπουτσια/πλατφορμες"
  },
  {
    "image": "/assets/images/γυναικεια/παπουτσια/σαγιοναρες.jpeg",
    "name": "Γυναικείες Σαγιονάρες",
    "url": "γυναικεια/παπουτσια/σαγιοναρες"
  },
  {
    "image": "/assets/images/γυναικεια/παπουτσια/σανδαλια.jpeg",
    "name": "Γυναικεία Σανδάλια",
    "url": "γυναικεια/παπουτσια/σανδαλια"
  },
  {
    "image": "/assets/images/γυναικεια/παπουτσια/τσοκαρα.jpeg",
    "name": "Γυναικεία Τσόκαρα",
    "url": "γυναικεια/παπουτσια/τσοκαρα"
  }
]
